CHANGES.rst
CONTRIBUTORS.rst
DEVELOP.rst
LICENSE.GPL
LICENSE.rst
MANIFEST.in
README.rst
setup.cfg
setup.py
docs/conf.py
docs/index.rst
src/rohberg/__init__.py
src/rohberg.elasticsearchblocks.egg-info/PKG-INFO
src/rohberg.elasticsearchblocks.egg-info/SOURCES.txt
src/rohberg.elasticsearchblocks.egg-info/dependency_links.txt
src/rohberg.elasticsearchblocks.egg-info/entry_points.txt
src/rohberg.elasticsearchblocks.egg-info/namespace_packages.txt
src/rohberg.elasticsearchblocks.egg-info/not-zip-safe
src/rohberg.elasticsearchblocks.egg-info/requires.txt
src/rohberg.elasticsearchblocks.egg-info/top_level.txt
src/rohberg/elasticsearchblocks/__init__.py
src/rohberg/elasticsearchblocks/configure.zcml
src/rohberg/elasticsearchblocks/interfaces.py
src/rohberg/elasticsearchblocks/permissions.zcml
src/rohberg/elasticsearchblocks/setuphandlers.py
src/rohberg/elasticsearchblocks/testing.py
src/rohberg/elasticsearchblocks/behaviors/__init__.py
src/rohberg/elasticsearchblocks/behaviors/configure.zcml
src/rohberg/elasticsearchblocks/behaviors/elastic_search_blocks.py
src/rohberg/elasticsearchblocks/bin/export_elasticsearch_data.py
src/rohberg/elasticsearchblocks/bin/extract_possible_lexicon_terms.py
src/rohberg/elasticsearchblocks/browser/__init__.py
src/rohberg/elasticsearchblocks/browser/configure.zcml
src/rohberg/elasticsearchblocks/browser/overrides/.gitkeep
src/rohberg/elasticsearchblocks/browser/static/.gitkeep
src/rohberg/elasticsearchblocks/controlpanels/__init__.py
src/rohberg/elasticsearchblocks/controlpanels/configure.zcml
src/rohberg/elasticsearchblocks/controlpanels/volto_searchkit_block_control_panel/__init__.py
src/rohberg/elasticsearchblocks/controlpanels/volto_searchkit_block_control_panel/configure.zcml
src/rohberg/elasticsearchblocks/controlpanels/volto_searchkit_block_control_panel/controlpanel.py
src/rohberg/elasticsearchblocks/locales/README.rst
src/rohberg/elasticsearchblocks/locales/__init__.py
src/rohberg/elasticsearchblocks/locales/rohberg.elasticsearchblocks.pot
src/rohberg/elasticsearchblocks/locales/update.py
src/rohberg/elasticsearchblocks/locales/update.sh
src/rohberg/elasticsearchblocks/locales/en/LC_MESSAGES/rohberg.elasticsearchblocks.po
src/rohberg/elasticsearchblocks/profiles/default/browserlayer.xml
src/rohberg/elasticsearchblocks/profiles/default/catalog.xml
src/rohberg/elasticsearchblocks/profiles/default/controlpanel.xml
src/rohberg/elasticsearchblocks/profiles/default/metadata.xml
