Metadata-Version: 2.1
Name: rohberg.elasticsearchblocks
Version: 1.0.0
Summary: Index Plone block text
Home-page: https://github.com/rohberg/rohberg.elasticsearchblocks
Author: Katja Süss
Author-email: k.suess@rohberg.ch
License: GPL version 2
Project-URL: PyPI, https://pypi.python.org/pypi/rohberg.elasticsearchblocks
Project-URL: Source, https://github.com/rohberg/rohberg.elasticsearchblocks
Project-URL: Tracker, https://github.com/rohberg/rohberg.elasticsearchblocks/issues
Keywords: Python Plone CMS
Classifier: Environment :: Web Environment
Classifier: Framework :: Plone
Classifier: Framework :: Plone :: Addon
Classifier: Framework :: Plone :: 5.2
Classifier: Framework :: Plone :: 6.0
Classifier: Programming Language :: Python
Classifier: Programming Language :: Python :: 3.8
Classifier: Programming Language :: Python :: 3.9
Classifier: Programming Language :: Python :: 3.10
Classifier: Programming Language :: Python :: 3.11
Classifier: Operating System :: OS Independent
Classifier: License :: OSI Approved :: GNU General Public License v2 (GPLv2)
Requires-Python: >=3.8
Provides-Extra: test
License-File: LICENSE.GPL
License-File: LICENSE.rst
